tractordriver/.gitignore
tractordriver/TractorScripts.py
tractordriver/WebElement.py
tractordriver/__init__.py
tractordriver/clientsidescripts.js
tractordriver/resource.py
tractordriver/webdriver.py
tractordriver-0.1.1.dist-info/entry_points.txt
tractordriver-0.1.1.dist-info/LICENSE
tractordriver-0.1.1.dist-info/LICENSE.orig
tractordriver-0.1.1.dist-info/WHEEL
tractordriver-0.1.1.dist-info/METADATA
tractordriver-0.1.1.dist-info/RECORD
